histo_patch/__init__.py
histo_patch/annotation.py
histo_patch/extract.py
histo_patch/histo_patch.py
histo_patch/scanner.py
histo_patch/utils.py
histo_patch-0.95.dist-info/LICENSE
histo_patch-0.95.dist-info/METADATA
histo_patch-0.95.dist-info/WHEEL
histo_patch-0.95.dist-info/entry_points.txt
histo_patch-0.95.dist-info/top_level.txt
histo_patch-0.95.dist-info/RECORD
