Metadata-Version: 2.1
Name: histo-patch
Version: 0.95
Summary: histopatch: image patch extraction from Whole Slide Images
Home-page: https://github.com/dakomura/histo_patch
Download-URL: https://github.com/dakomura/histo_patch
Author: Daisuke Komura
Author-email: kdais-prm@m.u-tokyo.ac.jp
Maintainer: Daisuke Komura
Maintainer-email: kdais-prm@m.u-tokyo.ac.jp
License: BSD 3-Clause
Classifier: Intended Audience :: Science/Research
Classifier: License :: OSI Approved :: BSD License
Classifier: Programming Language :: Python :: 3
Classifier: Programming Language :: Python :: 3.6
Classifier: Programming Language :: Python :: 3.7
Classifier: Programming Language :: Python :: 3.8
Classifier: Programming Language :: Python :: 3.9
Classifier: Programming Language :: Python :: 3 :: Only
Classifier: Topic :: Scientific/Engineering
Classifier: Topic :: Scientific/Engineering :: Visualization
Classifier: Topic :: Scientific/Engineering :: Artificial Intelligence
Classifier: Topic :: Multimedia :: Graphics
Requires-Python: >=3.6
License-File: LICENSE
Requires-Dist: tifffile (>=2022.5.4)
Requires-Dist: numpy (>=1.20.3)
Requires-Dist: tripy (>=1.0.0)
Requires-Dist: pyclipper (>=1.3.0)
Requires-Dist: opencv-python (>=4.6.0)
Requires-Dist: zarr (>=2.11.3)
Requires-Dist: imagecodecs (>=2022.2.22)
Requires-Dist: click (>=8.1.3)
Requires-Dist: Pillow (>=9.0.0)
